imgwtools/__init__.py
imgwtools/_version.py
imgwtools/config.py
imgwtools/exceptions.py
imgwtools/fetch.py
imgwtools/models.py
imgwtools/parsers.py
imgwtools/stations.py
imgwtools/urls.py
imgwtools/api/__init__.py
imgwtools/api/main.py
imgwtools/api/schemas.py
imgwtools/api/routes/__init__.py
imgwtools/api/routes/download.py
imgwtools/api/routes/hydro.py
imgwtools/api/routes/meteo.py
imgwtools/api/routes/pmaxtp.py
imgwtools/cli/__init__.py
imgwtools/cli/admin.py
imgwtools/cli/db.py
imgwtools/cli/fetch.py
imgwtools/cli/list_cmd.py
imgwtools/cli/main.py
imgwtools/core/__init__.py
imgwtools/core/imgw_api.py
imgwtools/core/imgw_datastore.py
imgwtools/core/imgw_spatial.py
imgwtools/core/url_builder.py
imgwtools/db/__init__.py
imgwtools/db/cache_manager.py
imgwtools/db/connection.py
imgwtools/db/models.py
imgwtools/db/parsers.py
imgwtools/db/repository.py
imgwtools/db/schema.py
imgwtools/web/__init__.py
imgwtools/web/app.py
imgwtools/web/static/css/style.css
imgwtools/web/static/js/app.js
imgwtools/web/templates/base.html
imgwtools/web/templates/index.html
imgwtools/web/templates/map.html
imgwtools/web/templates/download/hydro.html
imgwtools/web/templates/download/index.html
imgwtools/web/templates/download/meteo.html
imgwtools/web/templates/download/pmaxtp.html
imgwtools/web/templates/partials/download_links.html
imgwtools/web/templates/partials/error.html
imgwtools/web/templates/partials/pmaxtp_result.html
imgwtools/web/templates/partials/station_table.html
imgwtools/web/templates/stations/list.html
imgwtools-2.0.1.dist-info/METADATA
imgwtools-2.0.1.dist-info/WHEEL
imgwtools-2.0.1.dist-info/entry_points.txt
imgwtools-2.0.1.dist-info/licenses/LICENSE
imgwtools-2.0.1.dist-info/RECORD
