Metadata-Version: 2.4
Name: imgwtools
Version: 2.0.1
Summary: Python library for accessing IMGW (Polish Institute of Meteorology and Water Management) public data
Project-URL: Homepage, https://github.com/Daldek/IMGWTools
Project-URL: Repository, https://github.com/Daldek/IMGWTools
Project-URL: Issues, https://github.com/Daldek/IMGWTools/issues
Author-email: Piotr de Bever <git@debever.pl>
License-Expression: MIT
License-File: LICENSE
Keywords: data,hydrology,imgw,meteorology,pmaxtp,poland,precipitation,weather
Classifier: Development Status :: 4 - Beta
Classifier: Environment :: Console
Classifier: Environment :: Web Environment
Classifier: Intended Audience :: Developers
Classifier: Intended Audience :: Science/Research
Classifier: License :: OSI Approved :: MIT License
Classifier: Operating System :: OS Independent
Classifier: Programming Language :: Python :: 3
Classifier: Programming Language :: Python :: 3.11
Classifier: Programming Language :: Python :: 3.12
Classifier: Topic :: Scientific/Engineering :: Atmospheric Science
Classifier: Topic :: Scientific/Engineering :: GIS
Classifier: Topic :: Scientific/Engineering :: Hydrology
Classifier: Typing :: Typed
Requires-Python: >=3.11
Requires-Dist: httpx>=0.25
Requires-Dist: pydantic>=2.0
Provides-Extra: api
Requires-Dist: fastapi>=0.100; extra == 'api'
Requires-Dist: jinja2>=3.1; extra == 'api'
Requires-Dist: pydantic-settings>=2.0; extra == 'api'
Requires-Dist: python-multipart>=0.0.6; extra == 'api'
Requires-Dist: uvicorn[standard]>=0.24; extra == 'api'
Provides-Extra: cli
Requires-Dist: pydantic-settings>=2.0; extra == 'cli'
Requires-Dist: rich>=13.0; extra == 'cli'
Requires-Dist: typer>=0.9; extra == 'cli'
Provides-Extra: db
Requires-Dist: pydantic-settings>=2.0; extra == 'db'
Provides-Extra: dev
Requires-Dist: fastapi>=0.100; extra == 'dev'
Requires-Dist: jinja2>=3.1; extra == 'dev'
Requires-Dist: mypy>=1.6; extra == 'dev'
Requires-Dist: pandas>=2.0; extra == 'dev'
Requires-Dist: pydantic-settings>=2.0; extra == 'dev'
Requires-Dist: pyproj>=3.6; extra == 'dev'
Requires-Dist: pyshp>=2.3; extra == 'dev'
Requires-Dist: pytest-asyncio>=0.21; extra == 'dev'
Requires-Dist: pytest-cov>=4.1; extra == 'dev'
Requires-Dist: pytest>=7.4; extra == 'dev'
Requires-Dist: python-multipart>=0.0.6; extra == 'dev'
Requires-Dist: respx>=0.20; extra == 'dev'
Requires-Dist: rich>=13.0; extra == 'dev'
Requires-Dist: ruff>=0.1; extra == 'dev'
Requires-Dist: typer>=0.9; extra == 'dev'
Requires-Dist: uvicorn[standard]>=0.24; extra == 'dev'
Provides-Extra: full
Requires-Dist: fastapi>=0.100; extra == 'full'
Requires-Dist: jinja2>=3.1; extra == 'full'
Requires-Dist: pandas>=2.0; extra == 'full'
Requires-Dist: pydantic-settings>=2.0; extra == 'full'
Requires-Dist: pyproj>=3.6; extra == 'full'
Requires-Dist: pyshp>=2.3; extra == 'full'
Requires-Dist: python-multipart>=0.0.6; extra == 'full'
Requires-Dist: rich>=13.0; extra == 'full'
Requires-Dist: typer>=0.9; extra == 'full'
Requires-Dist: uvicorn[standard]>=0.24; extra == 'full'
Provides-Extra: spatial
Requires-Dist: pandas>=2.0; extra == 'spatial'
Requires-Dist: pyproj>=3.6; extra == 'spatial'
Requires-Dist: pyshp>=2.3; extra == 'spatial'
